README.rst
setup.py
wechat_sender/__init__.py
wechat_sender/compatible.py
wechat_sender/listener.py
wechat_sender/objects.py
wechat_sender/sender.py
wechat_sender/utils.py
wechat_sender.egg-info/PKG-INFO
wechat_sender.egg-info/SOURCES.txt
wechat_sender.egg-info/dependency_links.txt
wechat_sender.egg-info/requires.txt
wechat_sender.egg-info/top_level.txt
wechat_sender.egg-info/zip-safe