Metadata-Version: 1.1
Name: wechat-sender
Version: 0.1.4
Summary: 随时随地发送消息到微信
Home-page: https://github.com/bluedazzle/wechat_sender
Author: RaPoSpectre
Author-email: rapospectre@gmail.com
License: BSD
Keywords: Wechat,微信,监控
Platform: UNKNOWN
Classifier: License :: OSI Approved :: BSD License
Classifier: Programming Language :: Python
Classifier: Operating System :: OS Independent
Classifier: Topic :: Communications :: Chat
Classifier: Topic :: Utilities
Classifier: Programming Language :: Python :: 2.7
Classifier: Programming Language :: Python :: 3.6
